datapackage_pipelines_datahub/VERSION
datapackage_pipelines_datahub/__init__.py
datapackage_pipelines_datahub/processors/__init__.py
datapackage_pipelines_datahub/processors/dump/__init__.py
datapackage_pipelines_datahub/processors/dump/to_datahub.py
datapackage_pipelines_datahub-0.0.6.dist-info/DESCRIPTION.rst
datapackage_pipelines_datahub-0.0.6.dist-info/METADATA
datapackage_pipelines_datahub-0.0.6.dist-info/RECORD
datapackage_pipelines_datahub-0.0.6.dist-info/WHEEL
datapackage_pipelines_datahub-0.0.6.dist-info/metadata.json
datapackage_pipelines_datahub-0.0.6.dist-info/top_level.txt
