Metadata-Version: 2.0
Name: datapackage-pipelines-datahub
Version: 0.0.6
Summary: {{ DESCRIPTION }}
Home-page: https://github.com/datahq/datapackage_pipelines_datahub
Author: DataHQ
Author-email: UNKNOWN
License: MIT
Keywords: data,analytics
Platform: UNKNOWN
Classifier: Development Status :: 4 - Beta
Classifier: Environment :: Web Environment
Classifier: Intended Audience :: Developers
Classifier: License :: OSI Approved :: MIT License
Classifier: Operating System :: OS Independent
Classifier: Programming Language :: Python :: 3.6
Classifier: Topic :: Internet :: WWW/HTTP :: Dynamic Content
Classifier: Topic :: Software Development :: Libraries :: Python Modules
Requires-Dist: datapackage-pipelines
Provides-Extra: develop
Requires-Dist: pylama; extra == 'develop'
Requires-Dist: pytest; extra == 'develop'
Requires-Dist: pytest-cov; extra == 'develop'
Requires-Dist: tox; extra == 'develop'
